QLine/Constants.py
QLine/Grid.py
QLine/__init__.py
QLine/basis_functions.py
QLine/hamiltonian.py
QLine/math_methods.py
QLine/plotting.py
QLine/potentials.py
QLine/schroedinger_eq.py
QLine-1.2.dist-info/LICENSE
QLine-1.2.dist-info/METADATA
QLine-1.2.dist-info/WHEEL
QLine-1.2.dist-info/top_level.txt
QLine-1.2.dist-info/RECORD
